yacof/__init__.py
yacof/cli.py
yacof/conf.py
yacof/generator.py
yacof-0.0.3.dist-info/entry_points.txt
yacof-0.0.3.dist-info/LICENSE
yacof-0.0.3.dist-info/WHEEL
yacof-0.0.3.dist-info/METADATA
yacof-0.0.3.dist-info/RECORD
